viscy/__init__.py
viscy/_version.py
viscy/cli.py
viscy/data_organization.md
viscy/trainer.py
viscy/data/__init__.py
viscy/data/combined.py
viscy/data/ctmc_v1.py
viscy/data/distributed.py
viscy/data/gpu_aug.py
viscy/data/hcs.py
viscy/data/livecell.py
viscy/data/mmap_cache.py
viscy/data/segmentation.py
viscy/data/triplet.py
viscy/data/typing.py
viscy/preprocessing/generate_masks.py
viscy/preprocessing/pixel_ratio.py
viscy/preprocessing/precompute.py
viscy/preprocessing/preprocessing.md
viscy/representation/contrastive.py
viscy/representation/embedding_writer.py
viscy/representation/engine.py
viscy/representation/evaluation/__init__.py
viscy/representation/evaluation/clustering.py
viscy/representation/evaluation/dimensionality_reduction.py
viscy/representation/evaluation/distance.py
viscy/representation/evaluation/feature.py
viscy/representation/evaluation/lca.py
viscy/scripts/bench_augmentations.py
viscy/scripts/count_flops.py
viscy/scripts/curator_script.py
viscy/scripts/effective_receptive_field.py
viscy/scripts/export_from_tensorboard.py
viscy/scripts/fit_demo_contrastive.py
viscy/scripts/graphs_ConvNeXt_ResNet.py
viscy/scripts/load_ctmc_v1.py
viscy/scripts/load_livecell.py
viscy/scripts/log_feature_map.py
viscy/scripts/network_diagram.py
viscy/scripts/profile_dataloader.py
viscy/scripts/profile_dataloader.sh
viscy/scripts/profiling.py
viscy/scripts/recompute_phate.py
viscy/scripts/shared_dict.py
viscy/scripts/visualize_features.py
viscy/transforms/__init__.py
viscy/transforms/_gaussian_blur.py
viscy/transforms/_redef.py
viscy/transforms/_transforms.py
viscy/translation/engine.py
viscy/translation/evaluation.py
viscy/translation/evaluation_metrics.py
viscy/translation/predict_writer.py
viscy/unet/__init__.py
viscy/unet/networks/Unet25D.py
viscy/unet/networks/Unet2D.py
viscy/unet/networks/__init__.py
viscy/unet/networks/fcmae.py
viscy/unet/networks/unext2.py
viscy/unet/networks/layers/ConvBlock2D.py
viscy/unet/networks/layers/ConvBlock3D.py
viscy-0.3.3.dist-info/licenses/LICENSE
viscy-0.3.3.dist-info/METADATA
viscy-0.3.3.dist-info/WHEEL
viscy-0.3.3.dist-info/entry_points.txt
viscy-0.3.3.dist-info/top_level.txt
viscy-0.3.3.dist-info/RECORD
