Metadata-Version: 2.4
Name: viscy
Version: 0.3.3
Summary: computer vision for image-based phenotyping of single cells
Author-email: CZ Biohub SF <compmicro@czbiohub.org>
License-Expression: BSD-3-Clause
Classifier: Programming Language :: Python :: 3.11
Classifier: Programming Language :: Python :: 3.12
Classifier: Programming Language :: Python :: 3.13
Requires-Python: >=3.11
License-File: LICENSE
Requires-Dist: iohub<0.3,>=0.2.0
Requires-Dist: torch>=2.4.1
Requires-Dist: timm>=0.9.5
Requires-Dist: tensorboard>=2.13.0
Requires-Dist: lightning>=2.3.0
Requires-Dist: monai>=1.4.0
Requires-Dist: jsonargparse[signatures]>=4.20.1
Requires-Dist: scikit-image
Requires-Dist: matplotlib>=3.9.0
Requires-Dist: numpy
Requires-Dist: xarray
Requires-Dist: pytorch-metric-learning>2.0.0
Provides-Extra: metrics
Requires-Dist: cellpose>=3.0.10; extra == "metrics"
Requires-Dist: scikit-learn>=1.1.3; extra == "metrics"
Requires-Dist: imbalanced-learn>=0.12.0; extra == "metrics"
Requires-Dist: torchmetrics[detection]>=1.6.3; extra == "metrics"
Requires-Dist: ptflops>=0.7; extra == "metrics"
Requires-Dist: umap-learn; extra == "metrics"
Requires-Dist: captum>=0.7.0; extra == "metrics"
Requires-Dist: phate; extra == "metrics"
Provides-Extra: examples
Requires-Dist: napari; extra == "examples"
Requires-Dist: jupyter; extra == "examples"
Requires-Dist: jupytext; extra == "examples"
Provides-Extra: visual
Requires-Dist: ipykernel; extra == "visual"
Requires-Dist: graphviz; extra == "visual"
Requires-Dist: torchview; extra == "visual"
Requires-Dist: seaborn; extra == "visual"
Requires-Dist: plotly; extra == "visual"
Requires-Dist: nbformat; extra == "visual"
Requires-Dist: cmap; extra == "visual"
Provides-Extra: dev
Requires-Dist: viscy[examples,metrics,visual]; extra == "dev"
Requires-Dist: pytest; extra == "dev"
Requires-Dist: pytest-cov; extra == "dev"
Requires-Dist: hypothesis; extra == "dev"
Requires-Dist: ruff; extra == "dev"
Requires-Dist: profilehooks; extra == "dev"
Requires-Dist: onnxruntime; extra == "dev"
Dynamic: license-file
